{
 "20260719-R11C1": {
  "horodatage": "2026-07-19 14:16:08",
  "rapports": {
   "1": {
    "rapport": 19.0,
    "non_partant": false
   },
   "2": {
    "rapport": 96.0,
    "non_partant": false
   },
   "3": {
    "rapport": 17.0,
    "non_partant": false
   },
   "4": {
    "rapport": null,
    "non_partant": false
   },
   "5": {
    "rapport": 96.0,
    "non_partant": false
   },
   "6": {
    "rapport": 54.0,
    "non_partant": false
   },
   "7": {
    "rapport": 14.0,
    "non_partant": false
   },
   "8": {
    "rapport": 13.0,
    "non_partant": false
   },
   "9": {
    "rapport": 19.0,
    "non_partant": false
   },
   "10": {
    "rapport": 12.0,
    "non_partant": false
   },
   "11": {
    "rapport": 8.3,
    "non_partant": false
   },
   "12": {
    "rapport": 18.0,
    "non_partant": false
   },
   "13": {
    "rapport": 64.0,
    "non_partant": false
   },
   "14": {
    "rapport": 1.8,
    "non_partant": false
   }
  },
  "verrouillee": true
 },
 "20260719-R11C2": {
  "horodatage": "2026-07-19 14:46:14",
  "rapports": {
   "1": {
    "rapport": 34.0,
    "non_partant": false
   },
   "2": {
    "rapport": 29.0,
    "non_partant": false
   },
   "3": {
    "rapport": 103.0,
    "non_partant": false
   },
   "4": {
    "rapport": 17.0,
    "non_partant": false
   },
   "5": {
    "rapport": 5.0,
    "non_partant": false
   },
   "6": {
    "rapport": 13.0,
    "non_partant": false
   },
   "7": {
    "rapport": null,
    "non_partant": false
   },
   "8": {
    "rapport": null,
    "non_partant": false
   },
   "9": {
    "rapport": null,
    "non_partant": false
   },
   "10": {
    "rapport": 34.0,
    "non_partant": false
   },
   "11": {
    "rapport": 4.4,
    "non_partant": false
   },
   "12": {
    "rapport": 11.0,
    "non_partant": false
   },
   "13": {
    "rapport": 103.0,
    "non_partant": false
   },
   "14": {
    "rapport": 96.0,
    "non_partant": false
   },
   "15": {
    "rapport": 14.0,
    "non_partant": false
   },
   "16": {
    "rapport": 2.9,
    "non_partant": false
   }
  },
  "verrouillee": true
 },
 "20260719-R11C3": {
  "horodatage": "2026-07-19 15:16:18",
  "rapports": {
   "1": {
    "rapport": 4.6,
    "non_partant": false
   },
   "2": {
    "rapport": null,
    "non_partant": false
   },
   "3": {
    "rapport": null,
    "non_partant": false
   },
   "4": {
    "rapport": 8.5,
    "non_partant": false
   },
   "5": {
    "rapport": 22.0,
    "non_partant": false
   },
   "6": {
    "rapport": null,
    "non_partant": false
   },
   "7": {
    "rapport": 4.8,
    "non_partant": false
   },
   "8": {
    "rapport": 6.9,
    "non_partant": false
   },
   "9": {
    "rapport": 55.0,
    "non_partant": false
   },
   "10": {
    "rapport": 37.0,
    "non_partant": false
   },
   "11": {
    "rapport": 4.4,
    "non_partant": false
   },
   "12": {
    "rapport": 17.0,
    "non_partant": false
   },
   "13": {
    "rapport": 8.9,
    "non_partant": false
   }
  },
  "verrouillee": true
 },
 "20260719-R11C4": {
  "horodatage": "2026-07-19 15:46:25",
  "rapports": {
   "1": {
    "rapport": 18.0,
    "non_partant": false
   },
   "2": {
    "rapport": 92.0,
    "non_partant": false
   },
   "3": {
    "rapport": 69.0,
    "non_partant": false
   },
   "4": {
    "rapport": null,
    "non_partant": false
   },
   "5": {
    "rapport": null,
    "non_partant": false
   },
   "6": {
    "rapport": 27.0,
    "non_partant": false
   },
   "7": {
    "rapport": 23.0,
    "non_partant": false
   },
   "8": {
    "rapport": 9.5,
    "non_partant": false
   },
   "9": {
    "rapport": 2.4,
    "non_partant": false
   },
   "10": {
    "rapport": 16.0,
    "non_partant": false
   },
   "11": {
    "rapport": 13.0,
    "non_partant": false
   },
   "12": {
    "rapport": 3.0,
    "non_partant": false
   },
   "13": {
    "rapport": 30.0,
    "non_partant": false
   }
  },
  "verrouillee": true
 },
 "20260719-R4C4": {
  "horodatage": "2026-07-19 15:46:25",
  "rapports": {
   "1": {
    "rapport": 56.0,
    "non_partant": false
   },
   "2": {
    "rapport": 46.0,
    "non_partant": false
   },
   "3": {
    "rapport": null,
    "non_partant": true
   },
   "4": {
    "rapport": 5.0,
    "non_partant": false
   },
   "5": {
    "rapport": 127.0,
    "non_partant": false
   },
   "6": {
    "rapport": 12.0,
    "non_partant": false
   },
   "7": {
    "rapport": 161.0,
    "non_partant": false
   },
   "8": {
    "rapport": 23.0,
    "non_partant": false
   },
   "9": {
    "rapport": 4.3,
    "non_partant": false
   },
   "10": {
    "rapport": 70.0,
    "non_partant": false
   },
   "11": {
    "rapport": 5.3,
    "non_partant": false
   },
   "12": {
    "rapport": 12.0,
    "non_partant": false
   },
   "13": {
    "rapport": 135.0,
    "non_partant": false
   },
   "14": {
    "rapport": 29.0,
    "non_partant": false
   },
   "15": {
    "rapport": 161.0,
    "non_partant": false
   },
   "16": {
    "rapport": 33.0,
    "non_partant": false
   },
   "17": {
    "rapport": 5.0,
    "non_partant": false
   }
  }
 },
 "20260719-R11C5": {
  "horodatage": "2026-07-19 15:46:26",
  "rapports": {
   "1": {
    "rapport": null,
    "non_partant": false
   },
   "2": {
    "rapport": null,
    "non_partant": false
   },
   "3": {
    "rapport": null,
    "non_partant": false
   },
   "4": {
    "rapport": null,
    "non_partant": false
   },
   "5": {
    "rapport": null,
    "non_partant": false
   },
   "6": {
    "rapport": null,
    "non_partant": false
   },
   "7": {
    "rapport": 8.5,
    "non_partant": false
   },
   "8": {
    "rapport": 5.7,
    "non_partant": false
   },
   "9": {
    "rapport": 4.2,
    "non_partant": false
   },
   "10": {
    "rapport": null,
    "non_partant": false
   },
   "11": {
    "rapport": 4.2,
    "non_partant": false
   },
   "12": {
    "rapport": null,
    "non_partant": false
   },
   "13": {
    "rapport": 2.4,
    "non_partant": false
   },
   "14": {
    "rapport": null,
    "non_partant": false
   }
  }
 }
}